src/__init__.py
src/client.py
src/server.py
mcp_airflow_postgres-0.1.3.dist-info/METADATA
mcp_airflow_postgres-0.1.3.dist-info/WHEEL
mcp_airflow_postgres-0.1.3.dist-info/entry_points.txt
mcp_airflow_postgres-0.1.3.dist-info/RECORD
