Metadata-Version: 2.4
Name: mcp-airflow-postgres
Version: 0.1.3
Summary: Model Context Protocol (MCP) server for Airflow database integration
Author: Gavin Huang
License: MIT
Keywords: airflow,database,mcp,postgresql
Classifier: License :: OSI Approved :: MIT License
Classifier: Operating System :: OS Independent
Classifier: Programming Language :: Python :: 3
Classifier: Programming Language :: Python :: 3.10
Requires-Python: <4.0,>=3.10
Requires-Dist: fastmcp>=2.3.1
Requires-Dist: psycopg2-binary>=2.9.6
Requires-Dist: sqlalchemy>=2.0.0
Provides-Extra: dev
Requires-Dist: black>=23.3.0; extra == 'dev'
Requires-Dist: isort>=5.12.0; extra == 'dev'
Requires-Dist: mypy>=1.3.0; extra == 'dev'
Requires-Dist: pytest>=7.3.1; extra == 'dev'
